async_2captcha/__init__.py
async_2captcha/client.py
async_2captcha/enums.py
async_2captcha/http_session.py
async_2captcha/running_task.py
async_2captcha/types.py
async_2captcha/utils.py
async_2captcha/errors/__init__.py
async_2captcha/errors/client_errors.py
async_2captcha/errors/http_errors.py
async_2captcha/models/__init__.py
async_2captcha/models/base.py
async_2captcha/models/task.py
async_2captcha/solvers/__init__.py
async_2captcha/solvers/base.py
async_2captcha/solvers/coordinates.py
async_2captcha/solvers/turnstile.py
async_2captcha-0.1.7.dist-info/LICENSE
async_2captcha-0.1.7.dist-info/METADATA
async_2captcha-0.1.7.dist-info/WHEEL
async_2captcha-0.1.7.dist-info/top_level.txt
async_2captcha-0.1.7.dist-info/RECORD
