Metadata-Version: 2.2
Name: async-2captcha
Version: 0.1.7
Summary: An asynchronous Python client for the 2Captcha API.
Author-email: Dmitry <diprog991@gmail.com>
License: MIT License
Project-URL: Homepage, https://github.com/diprog/async-2captcha
Project-URL: Telegram, https://t.me/groowo
Project-URL: Repository, https://github.com/diprog/async-2captcha
Project-URL: Issue Tracker, https://github.com/diprog/async-2captcha/issues
Keywords: 2captcha,async,captcha-solving,captcha
Classifier: Development Status :: 3 - Alpha
Classifier: Intended Audience :: Developers
Classifier: Topic :: Software Development :: Libraries :: Python Modules
Classifier: License :: OSI Approved :: MIT License
Classifier: Programming Language :: Python
Classifier: Programming Language :: Python :: 3.8
Classifier: Programming Language :: Python :: 3.9
Classifier: Programming Language :: Python :: 3.10
Classifier: Programming Language :: Python :: 3.11
Requires-Python: >=3.8
License-File: LICENSE
Requires-Dist: pydantic>=2.10.6
Requires-Dist: httpx>=0.28.1
